wor/__init__.py
wor/xdg_open.py
pyxdg_open-0.2.1.dist-info/WHEEL
pyxdg_open-0.2.1.dist-info/entry_points.txt
pyxdg_open-0.2.1.dist-info/DESCRIPTION.rst
pyxdg_open-0.2.1.dist-info/top_level.txt
pyxdg_open-0.2.1.dist-info/metadata.json
pyxdg_open-0.2.1.dist-info/dependency_links.txt
pyxdg_open-0.2.1.dist-info/RECORD
pyxdg_open-0.2.1.dist-info/METADATA
