Metadata-Version: 2.0
Name: pyxdg-open
Version: 0.2.1
Summary: Opens URL or file in user preferred application (xdg-open replacement).
Home-page: https://github.com/wor/pyxdg-open
Author: Esa Määttä
Author-email: esa.maatta@iki.fi
License: GPL3
Keywords: python library desktop
Platform: UNKNOWN
Classifier: Development Status :: 4 - Beta
Classifier: License :: OSI Approved :: GNU General Public License v3 or later (GPLv3+)
Classifier: Operating System :: POSIX :: Linux
Classifier: Programming Language :: Python :: 3
Classifier: Topic :: Utilities
Requires-Dist: desktop-file-parser
Requires-Dist: Magic-file-extensions
